whoop_sdk/__init__.py
whoop_sdk/auth.py
whoop_sdk/client.py
whoop_sdk/mcp/__init__.py
whoop_sdk/mcp/__main__.py
whoop_sdk/mcp/server.py
whoop_sdk-0.3.1.dist-info/licenses/LICENSE
whoop_sdk-0.3.1.dist-info/METADATA
whoop_sdk-0.3.1.dist-info/WHEEL
whoop_sdk-0.3.1.dist-info/entry_points.txt
whoop_sdk-0.3.1.dist-info/top_level.txt
whoop_sdk-0.3.1.dist-info/RECORD
