Metadata-Version: 2.4
Name: whoop-sdk
Version: 0.3.1
Summary: A modern Python SDK for the WHOOP Developer API (v2)
Author-email: Eric Flynn <ejflynn27@gmail.com>
License: MIT
Project-URL: Homepage, https://github.com/ericfflynn/whoop-sdk
Project-URL: Repository, https://github.com/ericfflynn/whoop-sdk
Requires-Python: >=3.10
License-File: LICENSE
Requires-Dist: requests>=2.32.0
Requires-Dist: python-dotenv>=1.0.0
Requires-Dist: mcp>=1.1.2
Dynamic: license-file
